odoo/addons/account_invoice_supplierinfo_update_qty_multiplier/README.rst
odoo/addons/account_invoice_supplierinfo_update_qty_multiplier/__init__.py
odoo/addons/account_invoice_supplierinfo_update_qty_multiplier/__manifest__.py
odoo/addons/account_invoice_supplierinfo_update_qty_multiplier/i18n/account_invoice_supplierinfo_update_qty_multiplier.pot
odoo/addons/account_invoice_supplierinfo_update_qty_multiplier/i18n/fr.po
odoo/addons/account_invoice_supplierinfo_update_qty_multiplier/i18n/it.po
odoo/addons/account_invoice_supplierinfo_update_qty_multiplier/models/__init__.py
odoo/addons/account_invoice_supplierinfo_update_qty_multiplier/models/account_move_line.py
odoo/addons/account_invoice_supplierinfo_update_qty_multiplier/readme/DESCRIPTION.rst
odoo/addons/account_invoice_supplierinfo_update_qty_multiplier/static/description/icon.png
odoo/addons/account_invoice_supplierinfo_update_qty_multiplier/static/description/index.html
odoo/addons/account_invoice_supplierinfo_update_qty_multiplier/tests/__init__.py
odoo/addons/account_invoice_supplierinfo_update_qty_multiplier/tests/test_module.py
odoo/addons/account_invoice_supplierinfo_update_qty_multiplier/wizard/__init__.py
odoo/addons/account_invoice_supplierinfo_update_qty_multiplier/wizard/wizard_update_invoice_supplierinfo.xml
odoo/addons/account_invoice_supplierinfo_update_qty_multiplier/wizard/wizard_update_invoice_supplierinfo_line.py
odoo_addon_account_invoice_supplierinfo_update_qty_multiplier-16.0.1.0.0.4.dist-info/METADATA
odoo_addon_account_invoice_supplierinfo_update_qty_multiplier-16.0.1.0.0.4.dist-info/WHEEL
odoo_addon_account_invoice_supplierinfo_update_qty_multiplier-16.0.1.0.0.4.dist-info/top_level.txt
odoo_addon_account_invoice_supplierinfo_update_qty_multiplier-16.0.1.0.0.4.dist-info/RECORD
