Metadata-Version: 2.1
Name: odoo-addon-account_invoice_supplierinfo_update_qty_multiplier
Version: 16.0.1.0.0.4
Summary: In the invoice Supplierinfo wizard, allow to change the Quantity Multiplier field
Home-page: https://github.com/OCA/account-invoicing
Author: GRAP,Odoo Community Association (OCA)
Author-email: support@odoo-community.org
License: AGPL-3
Classifier: Programming Language :: Python
Classifier: Framework :: Odoo
Classifier: Framework :: Odoo :: 16.0
Classifier: License :: OSI Approved :: GNU Affero General Public License v3
Requires-Python: >=3.10
Requires-Dist: odoo-addon-account-invoice-supplierinfo-update<16.1dev,>=16.0dev
Requires-Dist: odoo-addon-product-supplierinfo-qty-multiplier<16.1dev,>=16.0dev
Requires-Dist: odoo<16.1dev,>=16.0a
